<?xml version="1.0" encoding="utf-8" ?>
<dwsync>
<file name="add.png" server="ldvwebcot01.www.purdue.edu//var/www/html/root/cot/" local="129875205500000000" remote="130264213660000000" />
<file name="blue-button.png" server="ldvwebcot01.www.purdue.edu//var/www/html/root/cot/" local="129875205500000000" remote="130264213660000000" />
<file name="circle-arrow-small.png" server="ldvwebcot01.www.purdue.edu//var/www/html/root/cot/" local="129875205500000000" remote="130264213660000000" />
<file name="gray-grad.png" server="ldvwebcot01.www.purdue.edu//var/www/html/root/cot/" local="129875205500000000" remote="130264213660000000" />
<file name="green-button.png" server="ldvwebcot01.www.purdue.edu//var/www/html/root/cot/" local="129875205500000000" remote="130264213660000000" />
<file name="red-button.png" server="ldvwebcot01.www.purdue.edu//var/www/html/root/cot/" local="129875205500000000" remote="130264213670000000" />
<file name="search-button-tile.png" server="ldvwebcot01.www.purdue.edu//var/www/html/root/cot/" local="129875205500000000" remote="130264213670000000" />
<file name="shadow.png" server="ldvwebcot01.www.purdue.edu//var/www/html/root/cot/" local="129875205500000000" remote="130264213670000000" />
</dwsync>